VMH_Escher-1.7.9b2.data/data/etc/jupyter/nbconfig/notebook.d/escher.json
VMH_Escher-1.7.9b2.data/data/share/jupyter/nbextensions/escher/escher.min.js
VMH_Escher-1.7.9b2.data/data/share/jupyter/nbextensions/escher/escher.min.js.map
VMH_Escher-1.7.9b2.data/data/share/jupyter/nbextensions/escher/extension.js
escher/__init__.py
escher/plots.py
escher/urls.py
escher/util.py
escher/validate.py
escher/version.py
escher/static/escher.min.js
escher/static/escher.min.js.map
escher/static/extension.js
escher/static/package.json
escher/static/jsonschema/1-0-0
escher/templates/standalone.html
VMH_Escher-1.7.9b2.dist-info/METADATA
VMH_Escher-1.7.9b2.dist-info/WHEEL
VMH_Escher-1.7.9b2.dist-info/top_level.txt
VMH_Escher-1.7.9b2.dist-info/RECORD
