Metadata-Version: 2.1
Name: VMH_Escher
Version: 1.7.9b2
Summary: Escher: A Web Application for Building, Sharing, and Embedding Data-Rich Visualizations of Metabolic Pathways
Home-page: https://escher.github.io
Author: Zachary King
License: MIT
Keywords: visualization,pathway map,metabolism,genome-scale-model,web application,D3.js,biojs
Classifier: Development Status :: 5 - Production/Stable
Classifier: License :: OSI Approved :: MIT License
Classifier: Topic :: Scientific/Engineering
Classifier: Topic :: Scientific/Engineering :: Visualization
Classifier: Programming Language :: Python :: 3
Classifier: Programming Language :: Python :: 3.5
Classifier: Programming Language :: Python :: 3.6
Classifier: Programming Language :: Python :: 3.7
Classifier: Operating System :: OS Independent
Requires-Dist: Jinja2<4,>=3.0.3
Requires-Dist: pytest<5,>=4.0.1
Requires-Dist: cobra>=0.5.0
Requires-Dist: jsonschema<5,>=4.17.3
Requires-Dist: ipywidgets<8,>=7.7.0
Requires-Dist: pandas>=0.18
Provides-Extra: docs
Requires-Dist: sphinx<3,>=2.1.1; extra == "docs"
Requires-Dist: sphinx-rtd-theme<0.5,>=0.4.3; extra == "docs"
Requires-Dist: nbsphinx<0.5,>=0.4.2; extra == "docs"
Provides-Extra: jupyter
Requires-Dist: jupyterlab-widgets==1.1.1; extra == "jupyter"
Requires-Dist: jupyterlab==3.6.3; extra == "jupyter"
Provides-Extra: test
Requires-Dist: pytest<8,>=4.3.0; extra == "test"
